SpatialAccessibility/__init__.py
SpatialAccessibility/utils/__init__.py
SpatialAccessibility/utils/accessibility.py
SpatialAccessibility/utils/compare.py
spatialaccessibility-0.0.13.dist-info/METADATA
spatialaccessibility-0.0.13.dist-info/WHEEL
spatialaccessibility-0.0.13.dist-info/RECORD
