Metadata-Version: 2.3
Name: SpatialAccessibility
Version: 0.0.13
Summary: A Spatial Accessibility Calculation package
Project-URL: Homepage, https://github.com/wsqstar/SpatialAccessibility
Project-URL: Issues, https://github.com/wsqstar/SpatialAccessibility/issues
Author-email: Shiqi Wang <qtec@outlook.com>
Classifier: Operating System :: OS Independent
Classifier: Programming Language :: Python :: 3
Requires-Python: >=3.8
